{
  "animateLoading": true,
  "borderRadius": "{{appsmith.theme.borderRadius.appBorderRadius}}",
  "bottomRow": 95,
  "boxShadow": "none",
  "buttonColor": "{{appsmith.theme.colors.primaryColor}}",
  "buttonStyle": "PRIMARY",
  "buttonVariant": "PRIMARY",
  "disabledWhenInvalid": false,
  "dynamicBindingPathList": [
    {
      "key": "buttonColor"
    },
    {
      "key": "borderRadius"
    }
  ],
  "dynamicTriggerPathList": [
    {
      "key": "onClick"
    }
  ],
  "isDefaultClickDisabled": true,
  "isDisabled": false,
  "isLoading": false,
  "isVisible": true,
  "key": "r65xtxqkzq",
  "leftColumn": 29,
  "minWidth": 120,
  "mobileBottomRow": 22,
  "mobileLeftColumn": 31,
  "mobileRightColumn": 47,
  "mobileTopRow": 18,
  "needsErrorInfo": false,
  "onClick": "{{ButtonAction.UpdateSubmit();}}",
  "originalBottomRow": 106,
  "originalTopRow": 99,
  "parentId": "k6mnmq0kvc",
  "placement": "CENTER",
  "recaptchaType": "V3",
  "renderMode": "CANVAS",
  "resetFormOnClick": false,
  "responsiveBehavior": "hug",
  "rightColumn": 56,
  "text": "Update",
  "topRow": 88,
  "type": "BUTTON_WIDGET",
  "version": 1,
  "widgetId": "ndr0fy4w10",
  "widgetName": "ModalUpdateButton"
}