{
  "gitSyncId": "68b6a5f1ec8af07165cbba50_d20dfb30-9615-4e38-9640-8c0c72d961bc",
  "id": "social token search_ButtonAction.form_reset",
  "pluginId": "js-plugin",
  "pluginType": "JS",
  "unpublishedAction": {
    "actionConfiguration": {
      "encodeParamsToggle": true,
      "jsArguments": [],
      "paginationType": "NONE",
      "timeoutInMillisecond": 10000
    },
    "clientSideExecution": true,
    "collectionId": "social token search_ButtonAction",
    "confirmBeforeExecute": false,
    "datasource": {
      "isAutoGenerated": false,
      "name": "UNUSED_DATASOURCE",
      "pluginId": "js-plugin"
    },
    "dynamicBindingPathList": [
      {
        "key": "body"
      }
    ],
    "fullyQualifiedName": "ButtonAction.form_reset",
    "name": "form_reset",
    "pageId": "social token search",
    "runBehaviour": "MANUAL",
    "userSetOnLoad": false
  }
}